autowzry_cli/__init__.py
autowzry_cli/run.py
autowzry_cli/进入autowzry文件夹查看运行方法.txt
autowzry_cli/autowzry/A0使用方法.txt
autowzry_cli/autowzry/B_单独运行体验服更新.bat
autowzry_cli/autowzry/B_单独运行王者营地.bat
autowzry_cli/autowzry/README.md
autowzry_cli/autowzry/WZRY.0.调试文件.txt
autowzry_cli/autowzry/WZRY.0.运行模式.txt
autowzry_cli/autowzry/WZRY.图片更新.txt
autowzry_cli/autowzry/WZTY.0.初始化.txt
autowzry_cli/autowzry/WZYD.0.初始化.txt
autowzry_cli/autowzry/autowzry.exe
autowzry_cli/autowzry/tpl1756468472227.png
autowzry_cli/autowzry/使用配置文件运行.bat
autowzry_cli-0.0.2a8.dist-info/licenses/LICENSE
autowzry_cli-0.0.2a8.dist-info/METADATA
autowzry_cli-0.0.2a8.dist-info/WHEEL
autowzry_cli-0.0.2a8.dist-info/entry_points.txt
autowzry_cli-0.0.2a8.dist-info/top_level.txt
autowzry_cli-0.0.2a8.dist-info/RECORD
