Metadata-Version: 2.4
Name: autowzry-cli
Version: 0.0.2a8
Summary: A CLI launcher for autowzry.
License: Copyright (c) 2025 autowzry-cli
Project-URL: Homepage, https://github.com/cndaqiang/autowzry
Classifier: Development Status :: 3 - Alpha
Classifier: Intended Audience :: End Users/Desktop
Classifier: Operating System :: Microsoft :: Windows
Classifier: Programming Language :: Python :: 3
Classifier: Topic :: Utilities
Requires-Python: >=3.7
License-File: LICENSE
Dynamic: license-file
